spacy_crfsuite/__init__.py
spacy_crfsuite/about.py
spacy_crfsuite/bilou.py
spacy_crfsuite/compat.py
spacy_crfsuite/conll.py
spacy_crfsuite/crf_extractor.py
spacy_crfsuite/eval.py
spacy_crfsuite/features.py
spacy_crfsuite/markdown.py
spacy_crfsuite/serve.py
spacy_crfsuite/test.py
spacy_crfsuite/tokenizer.py
spacy_crfsuite/train.py
spacy_crfsuite/utils.py
spacy_crfsuite/visualize.py
spacy_crfsuite-1.7.0.dist-info/LICENSE
spacy_crfsuite-1.7.0.dist-info/METADATA
spacy_crfsuite-1.7.0.dist-info/WHEEL
spacy_crfsuite-1.7.0.dist-info/entry_points.txt
spacy_crfsuite-1.7.0.dist-info/top_level.txt
spacy_crfsuite-1.7.0.dist-info/RECORD
