Metadata-Version: 2.1
Name: spacy-crfsuite
Version: 1.7.0
Summary: spaCy pipeline component for CRF entity extraction
Home-page: https://github.com/talmago/spacy_crfsuite
Author: Tal Almagor
Author-email: almagoric@gmail.com
License: MIT
Classifier: Intended Audience :: Developers
Classifier: Intended Audience :: Science/Research
Classifier: License :: OSI Approved :: MIT License
Classifier: Programming Language :: Python
Classifier: Programming Language :: Python :: 3
Classifier: Programming Language :: Python :: 3.6
Classifier: Topic :: Scientific/Engineering
Requires-Python: >=3
License-File: LICENSE
Requires-Dist: sklearn-crfsuite
Requires-Dist: spacy
Requires-Dist: joblib
Requires-Dist: plac
